obj_observe/__init__.py
obj_observe/core.py
obj_observe/py.typed
obj_observe-0.1.5.dist-info/LICENSE
obj_observe-0.1.5.dist-info/METADATA
obj_observe-0.1.5.dist-info/WHEEL
obj_observe-0.1.5.dist-info/top_level.txt
obj_observe-0.1.5.dist-info/RECORD
