Metadata-Version: 2.1
Name: obj-observe
Version: 0.1.5
Summary: Transparent Object Change Observers for Python objects and dicts
Author-email: Traian <contact@tra1an.com>
License: MIT License
Project-URL: Homepage, https://github.com/ravegoth/obj-observe
Project-URL: Issues, https://github.com/ravegoth/obj-observe/issues
Project-URL: Source, https://github.com/ravegoth/obj-observe
Classifier: Development Status :: 3 - Alpha
Classifier: Intended Audience :: Developers
Classifier: License :: OSI Approved :: MIT License
Classifier: Programming Language :: Python
Classifier: Programming Language :: Python :: 3
Classifier: Programming Language :: Python :: 3 :: Only
Classifier: Programming Language :: Python :: 3.8
Classifier: Programming Language :: Python :: 3.9
Classifier: Programming Language :: Python :: 3.10
Classifier: Programming Language :: Python :: 3.11
Classifier: Programming Language :: Python :: 3.12
Classifier: Programming Language :: Python :: 3.13
Classifier: Topic :: Software Development :: Libraries
Classifier: Typing :: Typed
Requires-Python: >=3.8
License-File: LICENSE
